{"US": {"STD": {"Apxvoid": 1, "NickChipper": 2, "Bunnyhoppor": 3, "Melt": 4, "Samsa": 5, "deathstarV3": 6, "Insurrection": 7, "Thaven": 8, "CosplayGrill": 9, "Dan": 10, "Enrico": 11, "Tromic": 12, "StrifeCro": 13, "Bennidge": 14, "BustaJ": 15, "FAST44": 16, "glory": 17, "Zeddy": 18, "Slysssa": 19, "Sezoklo": 20, "dreamify": 21, "WildPants": 22, "dog": 23, "Monsanto": 24, "zlsjs": 25, "Impact": 26, "RobertJ": 27, "Zalae": 28, "Sevel": 29, "Alexstrasza": 30, "bloodyface": 31, "Celeritas": 32, "Eggowaffle": 33, "Pizza": 34, "Irae": 35, "LazyTurtle": 36, "Tteokbokki": 37, "patoyao": 38, "\uc990\ub514": 39, "jad346": 40, "PennySalem": 41, "Limecake": 42, "SteveD": 43, "Thund3r": 44, "Arawn": 45, "Vyy": 46, "Hunter": 47, "ImAMonster": 48, "Evilgod": 49, "Nails": 50, "VictorFalcon": 51, "VitorioRadke": 52, "aimbotrusher": 53, "Jia": 54, "PapaJason": 55, "HSKeDaiBiao": 56, "Rozz": 57, "Ch95120": 58, "Paulo": 59, "GamerRvg": 60, "hollow": 61, "DashingHenry": 62, "turtletime99": 63, "PeLanza": 64, "\u627f\u6cf0\u4e0d\u8981": 65, "\u0417\u043b\u043e\u0439\u0428\u0442\u0430\u043d": 66, "herusia": 67, "DeadDraw": 68, "Shuntakle": 69, "Cesky": 70, "ConMan": 71, "Dono": 72, "ETC": 73, "SubUss": 74, "DimitriKazov": 75, "Phnx": 76, "Dysk1ddy": 77, "Kyle": 78, "Sharkuu": 79, "Zahok": 80, "XtraCoolCat": 81, "Ridiculous": 82, "\u5e74\u7d42\u734e\u91d1": 83, "Ugdra": 84, "BeNice": 85, "Tues": 86, "FlameLord": 87, "darkduke": 88, "Akatsu": 89, "MrHyde": 90, "AvisGod": 91, "Haztlan": 92, "DeadlyMouse": 93, "Matroid": 94, "Jam": 95, "xavgoh": 96, "GucciMane": 97, "Imfiredup": 98, "eugenio": 99, "Mryagut": 100, "muzzy": 101, "FrostShad0w": 102, "ZhangFei": 103, "SilverByz": 104, "xprot": 105, "Wrackle": 106, "lnguagehackr": 107, "Lemon": 108, "Akira": 109, "Xavier": 110, "\u306b\u3093": 111, "CongChua": 112, "Furyhunter": 113, "foolzombi": 114, "tenergy": 115, "Alan870806": 116, "GodsWounds": 117, "Immaculate": 118, "BBAEK": 119, "okasinnsuke": 120, "THJester": 121, "Impyyyyy": 122, "Theo": 123, "Ostkaka": 124, "Kevor24": 125, "Matchstick": 126, "MaRu": 127, "Fox": 128, "Katsumi": 129, "Ricey": 130, "Darw1n": 131, "Maneio": 132, "Chiaki": 133, "Rajah": 134, "shuzoDS": 135, "Dewey": 136, "Jin": 137, "BlackMage": 138, "Ernestun": 139, "hiragi": 140, "SAI": 141, "kevin": 142, "\ub69c\uce58\ub69c\uce58": 143, "jobohan": 144, "ttigers": 145, "RumHam": 146, "Leoric": 147, "lambyseries": 148, "Perna": 149, "bieberfever": 150, "Vespasian": 151, "Fibonacci": 152, "lalasong": 153, "Jalexander": 154, "Insanity": 155, "Silkysmooth": 156, "Akumaker": 157, "Joaquin": 158, "Phil": 159, "Nickolias": 160, "fateos": 161, "FJKiMochiNa": 162, "elle": 163, "ZBL": 164, "ShutUpMcKee": 165, "Rolle": 166, "KiRu": 167, "robbodog": 168, "NeonBlue": 169, "Peixoto": 170, "DrEddy": 171, "Konor": 172, "suspense": 173, "PervyOldGuy": 174, "Galaxy": 175, "Tyfoon": 176, "Elrich": 177, "CozyKitten": 178, "Gimkung": 179, "bigbang": 180, "DrAce": 181, "WitchKling": 182, "Greg": 183, "Insom": 184, "Gutits": 185, "wiz": 186, "Mismal": 187, "Dolorys": 188, "Lifecoach": 189, "fcor": 190, "Eddie": 191, "dee5": 192, "Aster": 193, "cesinha": 194, "Rooftrellen": 195, "LordMaelnik": 196, "L4DCoach": 197, "Benchwarmer": 198, "vbay03": 199, "Terrifictaco": 200}, "WLD": {"rickymartin": 1, "ksr": 2, "RenoJackson": 3, "Starlight": 4, "Jonahrah": 5, "awedragon": 6, "BattMasile": 7, "fallout": 8, "taizar": 9, "Mentalistic": 10, "MaHZMOK": 11, "Mason": 12, "XxFroBro45xX": 13, "Yano": 14, "Guiseitsme": 15, "Gankplang": 16, "REFRESHMENTS": 17, "Memnarch": 18, "Ghostdog": 19, "Zeddy": 20, "Soycake": 21, "JBz": 22, "Yami": 23, "rGOD": 24, "BackinBlack": 25, "Ihackkids": 26, "Rami94": 27, "Ferin": 28, "Vineetss": 29, "Kohai": 30, "Gatito": 31, "MMMMMMMMMHMM": 32, "Moeglichkeit": 33, "LuckyTiger": 34, "DBowie": 35, "LOL": 36, "mooingsheep": 37, "GreenFiend": 38, "EpigPlayer": 39, "Hijodaikan": 40, "Loominarty": 41, "AdorableG": 42, "Lenose": 43, "Siveure": 44, "Tidal": 45, "Rom469": 46, "Elise": 47, "Ruixiang": 48, "Clark": 49, "\u307b\uff01": 50, "Mtgsquirrel": 51, "tobius": 52, "Xiggalo": 53, "Abdz": 54, "Fly": 55, "sleight": 56, "Buckslayer88": 57, "gorky": 58, "GetRekt": 59, "Dogma": 60, "pappalling": 61, "Hylung": 62, "GreasyPoncho": 63, "DUCKWORTH": 64, "Fishtamer": 65, "Muel": 66, "RoadDog": 67, "\u0e19\u0e49\u0e33\u0e21\u0e19\u0e15\u0e4c": 68, "Celdrid": 69, "KimiHaSpider": 70, "Osmar18": 71, "nhlnjfan1": 72, "SanEsteban": 73, "Lumble": 74, "Nikov": 75, "mraugustzz": 76, "Ryla": 77, "nhull": 78, "Razbivacha": 79, "Tangsin": 80, "Skeptic": 81, "AnomalousT": 82, "TioConejo": 83, "Oldgeezerr": 84, "THEPhyrexIAN": 85, "vitribit": 86, "Aroma": 87, "Tripz": 88, "Grondus": 89, "Delpi": 90, "FatNastyFart": 91, "HAISHESAMA": 92, "ScrollMakerA": 93, "drTama": 94, "Aurin": 95, "Xin": 96, "Oatza": 97, "\u4e2d\u534e\u6218\u72fc\u65e0\u9650\u8363\u5149": 98, "Weatherlight": 99, "TecoRaidboss": 100, "GetMeowth": 101, "XCrouton": 102, "pac2maN": 103, "Bort": 104, "Balyssa": 105, "TripleC": 106, "DangeRuss": 107, "YataGG": 108, "Sheeran": 109, "CONCERNEDMOM": 110, "Control": 111, "Herewillbe": 112, "Zenarius": 113, "\uc0c8\ubcbd\ub2ec\ube5b\ud5a5\uae30": 114, "Kane98": 115, "Purleta": 116, "yaz324": 117, "DEFCON2": 118, "ShiangChen": 119, "SilentNight": 120, "Le7gendary": 121, "P1q": 122, "Anarch": 123, "TostaDojen": 124, "Guessncheck": 125, "Jomo": 126, "FFFFFFirstly": 127, "Storm": 128, "GotY": 129, "Gutits": 130, "SamAnthony": 131, "Kite": 132, "finally": 133, "TheMagus": 134, "RedBV19": 135, "GabrielCA": 136, "Cashmoney": 137, "myLife": 138, "AUGIE": 139, "bwps": 140, "BlazeDraco26": 141, "SejuaniFlail": 142, "Margor": 143, "Bananaramic": 144, "AtomicGoat": 145, "Mercury": 146, "keithnumbers": 147, "itachi": 148, "jin": 149, "T1noble": 150, "EternalCov": 151, "magikman": 152, "JayExMachina": 153, "OGLam": 154, "Synapse": 155, "theladylunch": 156, "DaddyGoomba": 157, "Lykotic": 158, "trstowell": 159, "Cresselia": 160, "MasterJL": 161, "PedePano": 162, "VIP": 163, "Boberton118": 164, "Bernie": 165, "dextronaut": 166, "Bluemoon": 167, "MrYuppi": 168, "wobbuffet03": 169, "ACTIVIA": 170, "Nick": 171, "Dawidoff": 172, "Yilias": 173, "WhiteDelight": 174, "Sukka": 175, "Jael": 176, "DawnLover": 177, "Ancalagon111": 178, "APL": 179, "GGDomesticus": 180, "Naji": 181, "Shane": 182, "hinterland": 183, "Chillestial": 184, "ElectroSurge": 185, "TomboWombo": 186, "Hersir": 187, "LUCAZHUNTER": 188, "BattleOoze": 189, "dinowandi": 190, "Amrithar": 191, "VHLong": 192, "TheHitman": 193, "Hydreigon44": 194, "WILFRID": 195, "Tower12346": 196, "mcdm": 197, "kittycat": 198, "Playa": 199, "Nepgear": 200}}, "EU": {"STD": {"Senfglas": 1, "Jarla": 2, "\u0414\u0438\u043a\u0438\u0439\u0417\u0432\u0435\u0440\u044c": 3, "iprkolo": 4, "Elendil": 5, "etovityusha": 6, "Un33D": 7, "NikoLion": 8, "Alaa": 9, "Bunnyhoppor": 10, "ETC": 11, "Fenomeno": 12, "Sheis13": 13, "SlemLikeBOC": 14, "Zhotan": 15, "BBrode": 16, "SoMuchFUN": 17, "BoarControl": 18, "timpson": 19, "Frost": 20, "Neeck": 21, "Mindowner": 22, "SirBanana": 23, "zabi": 24, "glory": 25, "Allad": 26, "Rdu": 27, "YouKnowWP": 28, "Epos": 29, "batmanjr": 30, "Felzak": 31, "GroSSo": 32, "Stealth": 33, "Archeom": 34, "Sebokooo": 35, "Zuka": 36, "Fiery": 37, "Shroominator": 38, "yellowman": 39, "Minislash": 40, "magicgeek": 41, "SoleniumSol": 42, "skorek": 43, "Kachura": 44, "Crane333": 45, "mico": 46, "LoneWolf": 47, "Skambo": 48, "Daeroon": 49, "Liakoto": 50, "Kagot": 51, "Nylaxina": 52, "Babbelbox": 53, "Diamantis": 54, "XxSebekXx": 55, "Kal\u00e0xz": 56, "Kalas": 57, "Dendi": 58, "WhiteHare": 59, "dawido": 60, "reqvam": 61, "Kolento": 62, "Dario149": 63, "Ragnar": 64, "Turna": 65, "Macy": 66, "Takitdown": 67, "Nim": 68, "NickChipper": 69, "Theo": 70, "OliHelland7": 71, "Dazzar": 72, "Gaboumme": 73, "Pignas": 74, "Meati": 75, "RENMEN": 76, "PepeWins": 77, "Jyr": 78, "Vaiaah": 79, "lattosio": 80, "Nito": 81, "GoVEGAN": 82, "levik": 83, "Benfa": 84, "Ryuw": 85, "Mismal": 86, "DeadDraw": 87, "Flop": 88, "hanniballz2": 89, "AR7": 90, "HENK": 91, "Frenetic": 92, "Tromic": 93, "Immortal": 94, "Vektor": 95, "BoomX9": 96, "PoliteSniper": 97, "Viper": 98, "lex": 99, "Tony": 100, "BarKod": 101, "Infinax": 102, "oliech": 103, "A83650": 104, "Kirilovsky": 105, "pilou": 106, "Dalok": 107, "MrSholpan": 108, "Faeli": 109, "Paynetrain": 110, "F4F1": 111, "Sevel": 112, "GamdurPLelit": 113, "Affie": 114, "Nico2108": 115, "sleepiiYEYEL": 116, "Personagrata": 117, "Jesuisbob": 118, "lefffka": 119, "BBAEK": 120, "Paulo": 121, "MurrMcK": 122, "Nikitero": 123, "\u627f\u6cf0\u4e0d\u8981": 124, "fateos": 125, "LLIoKoJIaD": 126, "Ferrari430": 127, "Nerv": 128, "IslandcatCN": 129, "Furyhunter": 130, "ntR": 131, "Bravo": 132, "SkaiWalkurrr": 133, "Sephas": 134, "NariNari": 135, "Thomerio": 136, "Kham\u00fbl": 137, "Electrify": 138, "chpatro": 139, "PuyolLegend": 140, "BeNice": 141, "HuguitheDOG": 142, "Den52rus": 143, "Thavo": 144, "Ruben0000001": 145, "Gev": 146, "LastShadowz": 147, "riku97": 148, "Zeddy": 149, "Tudor": 150, "FlatEagle": 151, "Budilicious": 152, "Chrissy": 153, "Ortalionowy": 154, "Aimedshot": 155, "ChatonBrutal": 156, "Voxx": 157, "qwerty": 158, "zigaco": 159, "Zeeland": 160, "MaRu": 161, "Warma": 162, "FallnServant": 163, "Agazapado": 164, "Lemon": 165, "Teohden": 166, "Martyr": 167, "wiz": 168, "MegaBug": 169, "Zyrios": 170, "Pyropine": 171, "dealwithit": 172, "ritchie": 173, "BongDaCity": 174, "SieraN": 175, "freakkinside": 176, "FreddyB": 177, "NuRToN": 178, "Ghotus": 179, "tmn": 180, "AleksandarNS": 181, "Disciple": 182, "LordOleg": 183, "\u041a\u0443\u043a\u043e\u043b\u043a\u0430": 184, "\u041c\u043e\u0449\u043d\u044b\u0435\u0428\u0442\u0430\u043d\u044b": 185, "BustaJ": 186, "AVZ075": 187, "Django": 188, "WildRoses": 189, "Winse": 190, "Sigge": 191, "Montanaz0r": 192, "Louisdebou": 193, "Elefanti123": 194, "RedNebula": 195, "Bozzzton": 196, "Valarya": 197, "SectumSempra": 198, "Swate": 199, "Cptnkitty": 200}, "WLD": {"\u6771\u5317\u4e94\u5927\u4ed9": 1, "BoardKing": 2, "HiddenPants": 3, "Romulus": 4, "Hijodaikan": 5, "Kohai": 6, "PDeS": 7, "xfeather": 8, "Smudge": 9, "MrPlumcake": 10, "YourOpponent": 11, "Kingsbounty": 12, "Drskull": 13, "LuMb3rJ4cK": 14, "tutur": 15, "Dostoyevsky": 16, "needle": 17, "Lannister": 18, "Mahagony": 19, "exe": 20, "KILORK42": 21, "pac2maN": 22, "NoHope": 23, "Goku": 24, "SmellyHuffer": 25, "RubentjeW": 26, "TheDoctor": 27, "Little": 28, "anormal": 29, "Pepp": 30, "DUCKWORTH": 31, "Ryla": 32, "\u0420\u0430\u0433\u043d\u0430\u0440\u041b\u043e\u0434\u0431\u0440\u043e": 33, "fhh": 34, "Siveure": 35, "Malekith": 36, "FrenchDevil": 37, "Fotina": 38, "Creed": 39, "Nature": 40, "Nightwalk": 41, "Gerg\u0151": 42, "Kikiswip": 43, "Hamster": 44, "TeepTop": 45, "ivan": 46, "LOFSargeras": 47, "MeD": 48, "Horus92": 49, "Lidosh": 50, "Gugynot": 51, "Modo": 52, "FardHast": 53, "PetiPower": 54, "Qanik": 55, "gago797": 56, "\u8d85\u7d1a\u5fcd\u8005": 57, "TheGreatGoku": 58, "Zeljin": 59, "firechao": 60, "Texas": 61, "mixky": 62, "DeathsFathom": 63, "JohnGordon": 64, "\u0418\u0441\u043a\u0430\u043d\u0434\u0435\u0440": 65, "Berk": 66, "pyrogein": 67, "hakunamatata": 68, "KingConan": 69, "ShaneFalco": 70, "MichalH29": 71, "\u0410\u043a\u0443\u0448\u0435\u0440\u041b\u044e\u0434\u043e\u0435\u0434": 72, "Smusic92": 73, "YechedMat": 74, "INTEFIX": 75, "BorodachHS": 76, "DestructYou": 77, "Ethardoth": 78, "noobfromLS": 79, "Pummer": 80, "XxFroBro45xX": 81, "Ryan": 82, "Zaharzahar": 83, "deadpiggy": 84, "Alb987": 85, "CoolKiller": 86, "Mozenrath": 87, "Aqua": 88, "Magma004": 89, "BLACKSTAR": 90, "AzureWrath": 91, "Maxerius": 92, "M\u00f8rbeck": 93, "XerxesBreak": 94, "\u041a\u0435\u0442\u0447\u0443\u043f": 95, "Thoughtseize": 96, "Counselor": 97, "RnGHSGod": 98, "Jonahrah": 99, "Norgok": 100, "Mats17": 101, "No3558": 102, "laitithai": 103, "Lasagne": 104, "sonofsun": 105, "Gentar": 106, "Uffffff": 107, "Pemmin": 108, "Erasme": 109, "Jerry97": 110, "N999": 111, "invoker": 112, "LuzKiddo": 113, "\u0427\u0430\u0439\u043d\u044b\u0439\u043e\u0442\u0435\u0446": 114, "muldek": 115, "lex": 116, "Ixlavok": 117, "Kabo": 118, "Mhs1994": 119, "The5thOldGod": 120, "DoctorBBF": 121, "AuroraHunter": 122, "Slater": 123, "costaskamby": 124, "Bellyguru": 125, "Man\u00e9lidas": 126, "CocoZohan": 127, "chris9822": 128, "Pain": 129, "yatous": 130, "DarthJack": 131, "AcidRock": 132, "sipiwi94": 133, "Faramir": 134, "Bixente": 135, "Snuffzz": 136, "m3s": 137, "abominio123": 138, "firestarter": 139, "Sisco": 140, "Jack75": 141, "Duck": 142, "Specialist": 143, "ljh": 144, "Avi": 145, "Adanthar": 146, "Pasi": 147, "Fiat500": 148, "Flauros97": 149, "JackBattle": 150, "Redefinee": 151, "notmyface": 152, "MgDuck": 153, "Diegolito": 154, "Session": 155, "Eddetektor": 156, "TradeLord": 157, "Mario": 158, "adelkzn": 159, "\u5624\u5624\u5624": 160, "Makcmakc": 161, "irini": 162, "OoJunjinoO": 163, "JustJ": 164, "teruteruboy": 165, "bluerabbit": 166, "Enzo1351": 167, "Leiva": 168, "Dajmond": 169, "LuckyTiger": 170, "casarisk": 171, "JungleBattle": 172, "Haffax": 173, "nisaasz": 174, "Shane": 175, "Cyrakusa": 176, "Echye": 177, "Constanton": 178, "Wojin": 179, "Woetah": 180, "RockNRolla": 181, "ZAHASMADAN": 182, "Eregost": 183, "Nanji": 184, "h\u00fc\u00fcbi": 185, "MajorTom": 186, "TheGuardian": 187, "Dezox": 188, "Kyomaku": 189, "\u0418\u0449\u0438\u041e\u0448\u0438\u0431\u043a\u0438": 190, "Mleiva": 191, "Catharsis": 192, "F\u00edlaCz": 193, "Silvio": 194, "Lawilet": 195, "Aefar": 196, "\u7dd2\u5948\u840c": 197, "Asurum": 198, "DanFortesque": 199, "SirPuFFaRiN": 200}}, "AP": {"STD": {"Definition": 1, "RaFaEl": 2, "fire": 3, "FUWAWA": 4, "Surrender": 5, "kagome": 6, "\u9db4\u8c37\u30c7\u30b9\u30a6\u30a3\u30f3\u30b0": 7, "Franklin": 8, "\uc1a8\ud30c\ub974\ud0c0": 9, "SoloTu": 10, "\ubb3c\ub9ac\uc655": 11, "rascal": 12, "Dan": 13, "oyatsu": 14, "\u627f\u6cf0\u4e0d\u8981": 15, "glory": 16, "Kangaskhan27": 17, "Cesky": 18, "\u5433\u67cf\u5112": 19, "\u0414\u0438\u043a\u0438\u0439\u0417\u0432\u0435\u0440\u044c": 20, "Andyzzz": 21, "Lokyin": 22, "on9yc": 23, "Shaxy": 24, "Korea": 25, "\u30d7\u30e9\u30b9": 26, "\uc624\ube60\ucc28": 27, "\ub69c\uce58\ub69c\uce58": 28, "\u96f7\u514b\u85a9": 29, "\u305f\u304b\u3084\u3093": 30, "Django": 31, "\u9b54\u6cd5\u5c11\u5a66\u5c0f\u5713": 32, "\u5b89\u4f60\u597d\u6211\u4e09\u6b72": 33, "Bath": 34, "sinah": 35, "gyu": 36, "muhi": 37, "\ud55c\uad6d\uc758\ub371\uba54\uc774\ucee4": 38, "COLDPLAY": 39, "\u3042\u308c\u3063\u304f\u3059": 40, "b787": 41, "\u6fb3\u9580\u9996\u5bb6\u7dda\u4e0a\u8ced\u5834": 42, "\u51b0\u6dc7\u6dcb": 43, "\uac00\ub098\ub2e4": 44, "Sheep": 45, "Bryant": 46, "Gosh": 47, "\u304b\u306b": 48, "\uc790\uc720\uc870\ud1f4\uad8c": 49, "kiryu": 50, "FuYuNoSoNaTa": 51, "Asura": 52, "tom60229": 53, "Hi3": 54, "\ub179\ud134\uc624\ube60\ubd88\uc880\uaebc\uc918": 55, "\ubbf8\ub974\ub2d8": 56, "\uae08\uc694\uc77c": 57, "\uc778\uc0dd\uc758\uac78\ub9bc\ub3cc\uac9c": 58, "\uc5f0\ub450\ubd80": 59, "AcaCia": 60, "Garchomp": 61, "Bodaybo": 62, "blitzchung": 63, "Fungggg": 64, "\u6346\u7c73": 65, "Eric": 66, "\u3058\u3085\u3093\u3084": 67, "youhit": 68, "MegaGliscor": 69, "chunglxx": 70, "\u7121\u540d\u5352\u4ed4": 71, "SubUss": 72, "hiragi": 73, "Pizza": 74, "BBAEK": 75, "\u57f7\u5ff5\u306e\u84bc\u6c41": 76, "Eason": 77, "herusia": 78, "\u5c71\u4e0b\u667a\u4e45": 79, "\u507d\u4e73\u7537": 80, "Rajah": 81, "kevinkao": 82, "AlwaysAwake": 83, "Arrowy": 84, "maxchen": 85, "Luna": 86, "\ub77c\uc774\uc5b8": 87, "Sonagi": 88, "HAYATA": 89, "\u3070\u304b\u3058\u3083\u306a\u3044": 90, "\u5feb\u6a02\u4e4b\u6f5b\u884c\u8005": 91, "Ugdra": 92, "ADU": 93, "ColaPopcorn": 94, "ark": 95, "raizin": 96, "mpjpupjpms": 97, "Duelist": 98, "\uc54c\uc218\uc5c6\uc74c": 99, "\u306b\u3093": 100, "curry": 101, "\uc774\uc8fc\ub099\uc8fc\ub099": 102, "okasinnsuke": 103, "\uce74\uce74\ub85c\ud2b8": 104, "\ud2b8\uc704\uce58\uac00\uc9c4": 105, "Signal": 106, "\u9ebb\u7169": 107, "Wilbell": 108, "MrTen": 109, "\uc720\uc988": 110, "XiaoDai": 111, "Alan870806": 112, "DDoANi": 113, "DawN": 114, "\ub119\uce58\uc0ac\ub0e5\uafbc": 115, "TIZS": 116, "moso": 117, "ARAI": 118, "KiRu": 119, "\u5c0f\u5440\u5c0f\u6625\u8f9b": 120, "SilverHawk": 121, "\uc2b9\ub0e5\uc774": 122, "\uc5d8\ub80c\ub514\uc57c": 123, "GundamFlame": 124, "PrayForMeTW": 125, "\u3068\u307f\u30fc": 126, "HOH": 127, "Satellite": 128, "Edwin": 129, "\ucd08\uc624": 130, "Giru": 131, "Tesseract": 132, "ESSKEET1T": 133, "\ud3c9\ud654": 134, "tenergy": 135, "Khaius": 136, "\u6afb\u4eac\u5927\u76dc\u97d3\u4e0d\u67f1": 137, "\uc774\uc2a4\ud2f0": 138, "\u590f\u5a1c109": 139, "tamama": 140, "RakJo": 141, "\uc544\ub974\uce74\ub098": 142, "\uc0b4\uc544\uc788\ub294\uc591\uc2ec": 143, "rookieAC": 144, "horo": 145, "\ucd5c\uc11d\uc911": 146, "doughnut": 147, "akok": 148, "\u3068\u308a\u306b\u304f": 149, "masa": 150, "King": 151, "\uc6a9\uc774": 152, "\u306a\u3081\u3053": 153, "\uc13c\ud1a0": 154, "Perna": 155, "\u30c8\u30e9\u30ce\u30a8": 156, "Cassia": 157, "\u9f9c\u6bdb\u8001\u982d": 158, "\uc751\uc560\uc138\ub825": 159, "SilverName": 160, "Galaxy": 161, "\u9b6f\u9b6f\u7c73\u862d\u9054": 162, "ZeLes": 163, "chy": 164, "emu": 165, "Momo": 166, "stelmosfire": 167, "\uc9c0\uc874\ud604\ubbfc\uc9f1": 168, "xenon": 169, "Kribo": 170, "\ub824\uad00\uc8fc\uc778": 171, "matsup": 172, "\u81ed\u80d6\u80d6": 173, "akaNte": 174, "Pacemak1r": 175, "Poolmaster": 176, "Roger": 177, "khaizero": 178, "\u8822\u8822\u8c6c": 179, "Tredsred": 180, "Gyong": 181, "\u963f\u54c7\u547e\u5580\u547e\u5566": 182, "Kuonet": 183, "lammy": 184, "\u304b\u3084\u306e\u3093": 185, "garubor0asia": 186, "\u3055\u3068\u3046\u3057\u304a": 187, "Switch": 188, "\uc544\uc774\uace0\uc778\uac04\uc544": 189, "LoNa": 190, "\u4e16\u754c\u96f2\u96f2\u4e0d\u7406\u4f60": 191, "Taeyeon": 192, "Matchstick": 193, "Duyyy": 194, "BigRoad": 195, "suspense": 196, "nsaids": 197, "takas": 198, "ToL": 199, "Volar": 200}, "WLD": {"BouncyBear": 1, "\u306f\u3044\u3057": 2, "Jaehyuk": 3, "\u3042\u304a\u3044": 4, "\u3066\u3063\u307a": 5, "\uc900\uad6c\ud30c\ud06c": 6, "ymeonhds": 7, "\uc2ec\uac01\ud558\uac8c\ubabb\ud568": 8, "\u5f88\u661f\u7206\u4f60\u77e5\u9053\u55ce": 9, "\uae55\ucff5\uc0b0": 10, "flugel": 11, "\uc0c8\ubcbd\ub2ec\ube5b\ud5a5\uae30": 12, "IIdollarCwon": 13, "\ub6f0\uc5b4\ubd24\uc790\ub0b4\uc190\uc548": 14, "bearkim": 15, "gyeol987": 16, "amokisak": 17, "Money": 18, "\uc18c\ubc29\ub300\uc6d0": 19, "\u30af\u30de\u30b7\u30f3": 20, "\uc0ac\uacfc\ub2f9": 21, "L4p1s": 22, "\ud560\ubc30": 23, "crong": 24, "sokuratesu": 25, "stardust": 26, "lIIIIIIIIIIl": 27, "SUNSHOWER": 28, "\uc724\ud55c": 29, "lmjb": 30, "\u30de\u30be\u304a\u3058\u3055\u3093": 31, "\uc810\uc2ec\uba38\uac85": 32, "Zakat": 33, "Bath": 34, "Answer9": 35, "Hotpink": 36, "\u963f\u51f1\u541b": 37, "zerg": 38, "JAK": 39, "\u6211\u6703\u6bba\u6b7b\u4f60": 40, "BillZF": 41, "\ud648\ub7f0\uc655": 42, "Muice": 43, "Kira": 44, "StoicTeemo": 45, "\uc81c\uac08\ub7c9": 46, "kitakami": 47, "Amalgamation": 48, "\uac90\uc9c0": 49, "\u4f0a\u9732\u6069": 50, "\u5510\u821c": 51, "Lagom": 52, "\ub9c8\uc2dc\ub8e8\ub9c1": 53, "\u6307\u53c9\u7403": 54, "SlugCat": 55, "YsLiang": 56, "\uc9c4\uc9c4\ub3cc\uc774": 57, "Rocketlin": 58, "\u5e0c\u9732": 59, "\uac10\uc9c8\ub9db": 60, "rui": 61, "\u5168\u91d1\u4f7f\u8005": 62, "Sun0822": 63, "King": 64, "\ube44\ud2c0\uc988\ubab0\ub798\uba39\uae30": 65, "\uc5d0\uc988": 66, "Ansh": 67, "Raizin": 68, "Akari": 69, "Backstab": 70, "ahiru": 71, "\u7684\u95dc\u7fbd": 72, "\uc624\ub2e4\uc19c": 73, "SONGXI": 74, "COLDPLAY": 75, "\ub300\ub098\ubb34\ud5ec\ub9ac\ucf65\ud130": 76, "BLUEORANGE": 77, "\u591a\u60c5\u4f3c\u7121\u60c5": 78, "Jeer": 79, "\u93e1\u82b1\u6c34\u6708": 80, "NDJIA": 81, "Gunbird": 82, "sss": 83, "\u840c\u5a18\u767e\u79d1": 84, "sodacityfunk": 85, "\ub9ac\ub77c\uc2a4": 86, "\u30de\u30c3\u30c1\u30e7": 87, "\uac00\uc7ac": 88, "\u4f60\u8cf4\u6771\u6771\u4e0d\u932f\u561b": 89, "\uc5d4\ud0a4": 90, "\u7528\u4e09\u5f35": 91, "\uc758\ubbf8": 92, "\ud76c\ub07c": 93, "linkinhoi": 94, "\u6697\u5f71\u98a8\u66b4": 95, "\ub124\ub188\uc744\ucd94\uaca9\ud574\uc8fc\ub9c8": 96, "Mayday": 97, "Shanimabe": 98, "\ub119\uce58\uc0ac\ub0e5\uafbc": 99, "\uc7a1\ucd08": 100, "awesome": 101, "\uc774\ub300\ub780\ub2d8": 102, "\ubcd1\uae30\ud0c4\uc57d\uacc4\uc6d0": 103, "HotFinger": 104, "\u56db\u516d\u4e5d\u516b\u4e5d\u4e00": 105, "RexChou": 106, "\u30d5\u30ed\u30b9\u30c8\u30d5\u30a3\u30fc\u30c8": 107, "AYAME016": 108, "Shalashaska": 109, "Ajiten": 110, "\uc529\uc529\ucda9": 111, "HauHin": 112, "\ud0dc\ud654\uc0ac": 113, "Session": 114, "suldabe": 115, "yuchom": 116, "\uc721\uace0\uae30\ud574\ubb3c\uc18c\uc2a4": 117, "\uc5f0\ud5a5": 118, "kouton03": 119, "RamonaFlower": 120, "\u8840\u98a8\u9913\u72fc": 121, "\ucd5c\uc131\uaddc": 122, "starplatinum": 123, "\ud070\uadf8\ub9bc": 124, "\u8c6c\u8c6c": 125, "WOLF66": 126, "\ud604\uc11d": 127, "\ub370\ub178": 128, "\u30c9\u30af\u307a": 129, "\ucd5c\uc911\uc6d0": 130, "\u304a\u3066\u3043\u304b": 131, "lummm": 132, "AyaseEli": 133, "tmo": 134, "\uae00\uc384": 135, "uka": 136, "\u8c93\u5c3e": 137, "Alsyboy": 138, "\u71c1\u9b54": 139, "Cresselia": 140, "\ubb3c\uae68": 141, "Bnetplayer": 142, "\u90a3\u6642\u8776\u98db": 143, "\u65e0\u8fb9\u843d\u6728": 144, "IF3ropeAllrp": 145, "Greepooh": 146, "whh": 147, "MrStRaNgE": 148, "Oshiken": 149, "ABC": 150, "solunar": 151, "ogutty": 152, "Rune": 153, "minecraft": 154, "Hatatagami": 155, "Dinghao": 156, "zfmosquito": 157, "\u7210\u77f3\u5916\u639b\u4ee3\u6253\u79c1\u6211": 158, "\uc774\uce74\ub8e8\uc2a4": 159, "GOLDBAREN": 160, "HIOCKY": 161, "Bang": 162, "DrHawk": 163, "\ud638\ub7ad\uc774\ub0d0": 164, "mpti": 165, "\uc2b9\uc0c1": 166, "Casol": 167, "\u5c0f\u5ae9\u74dc": 168, "\u96ea\u9719": 169, "Mushen": 170, "\u8d85\u7f3a\u5fb7\u7684\u5fb7\u9b6f\u4f0a": 171, "\uc9c1\ubc15\uad6c\ub9ac": 172, "August": 173, "hiroromura": 174, "\u9280\u98a8": 175, "Sallycanwait": 176, "Eis": 177, "Shane": 178, "escad": 179, "iamno1": 180, "\u6709\u6c92\u6709\u5f88\u6e96": 181, "BeOZ": 182, "Robin": 183, "\uc18c\ub9ac\uc5c6\ub294\uac80": 184, "Echoplex": 185, "LKEric": 186, "GuldanMASTER": 187, "summus": 188, "\ub8b0\ud55c": 189, "Nemo": 190, "way": 191, "Empt2exy": 192, "BigBossMan": 193, "Bruce": 194, "\u9023\u74b0": 195, "seahorse": 196, "Jdy": 197, "\ub2e4\ud06c\uc18c\uc6b8\ud558\uace0\uc2f6\ub139": 198, "Rainer": 199, "TrouserSnake": 200}}}