{"US": {"STD": {"Gaby": 1, "BruTo": 2, "MattP": 3, "WetGoose": 4, "Apollion": 5, "Elrich": 6, "DreadEye": 7, "GamerRvg": 8, "tholwmenos": 9, "Pizza": 10, "Eggowaffle": 11, "Jesuisbob": 12, "Komik": 13, "Impact": 14, "SATEAB": 15, "noblord": 16, "McBanterFace": 17, "wiRer": 18, "Mesmile": 19, "Theo": 20, "herusia": 21, "Ryan223437": 22, "Cassia": 23, "Kal\u00e0xz": 24, "Rooftrellen": 25, "bloodyface": 26, "Scorchy": 27, "hollow": 28, "Samsa": 29, "reqvam": 30, "Fungggg": 31, "FriedChicken": 32, "bobbyex": 33, "adultgiraffe": 34, "Cesky": 35, "DenBut": 36, "LordMaelnik": 37, "Tansoku": 38, "Leta": 39, "Turner": 40, "Archangel": 41, "killinallday": 42, "Furyhunter": 43, "Nails": 44, "PocketTrain": 45, "DimitriKazov": 46, "Flamekilla": 47, "Paperninja": 48, "Zany": 49, "Thund3r": 50, "CaelesLuna": 51, "Fibonacci": 52, "NoHandsGamer": 53, "Fled": 54, "k1ngkong": 55, "MegaGliscor": 56, "NaySyl": 57, "BoarControl": 58, "Germanshep": 59, "matff": 60, "SuperiorD": 61, "zlsjs": 62, "Srdjan": 63, "Turbon1ck": 64, "shanOz": 65, "Dreivo": 66, "TheLiquidOx": 67, "WildPants": 68, "RobertJ": 69, "iNsAnE": 70, "Elfangor": 71, "Enrico": 72, "WoT": 73, "shuijiao": 74, "FreddyB": 75, "Tyrano": 76, "rascal": 77, "Bunnyhoppor": 78, "UchihaSaske": 79, "PDA": 80, "Glasnost": 81, "Rase": 82, "dajz": 83, "LeoPrystupa": 84, "CheeseHead": 85, "Nalguidan": 86, "glory": 87, "BuckNastyZB": 88, "Taesang": 89, "BrianOBryan": 90, "oyatsu": 91, "N1mro": 92, "Zananananan": 93, "lambyseries": 94, "Deleuzer": 95, "bieberfever": 96, "LSVfanboy": 97, "Dono": 98, "ZBL": 99, "Pavelingbook": 100, "Hawkeye": 101, "Ethan": 102, "jambre": 103, "DouAhou": 104, "Orange": 105, "BadBoy": 106, "\u9999\u83c7\u597e\u6c41": 107, "DavidSWu": 108, "Ekrow": 109, "HyunMini": 110, "Tredsred": 111, "\u5c71\u4e0b\u667a\u4e45": 112, "Monsanto": 113, "Apxvoid": 114, "GeneralC": 115, "Patrick07": 116, "tamama": 117, "zlofany": 118, "maneti": 119, "blueblurr": 120, "patoyao": 121, "\u306d\u30fc\u3061\u3083\u3093": 122, "M1LAN": 123, "Aleph": 124, "DJT": 125, "insania": 126, "Macheen": 127, "gle": 128, "Lokyin": 129, "foghi8": 130, "UnlikelyHero": 131, "Lumken": 132, "Solojazz": 133, "Rks": 134, "Dmoney": 135, "muzzy": 136, "\u041f\u0430\u0448\u0430\u0422\u0435\u0445\u043d\u0438\u043a": 137, "\u9f9c\u6bdb\u8001\u982d": 138, "gostevo": 139, "riku97": 140, "kaiobbd": 141, "RobotWizard": 142, "N0lan": 143, "Empanizado": 144, "Klei": 145, "LoNa": 146, "Construct": 147, "Doaibu": 148, "BeterBabbit": 149, "Morrissey": 150, "songsongxian": 151, "Etoce": 152, "bchsrh": 153, "CosplayGrill": 154, "Itim": 155, "Theseus": 156, "WaningMoon": 157, "baenugget": 158, "lex": 159, "ThaLucky1": 160, "RumHam": 161, "BZRK": 162, "Odemian": 163, "Reliquary": 164, "DarthNihilus": 165, "MightyOwl": 166, "kukaloko": 167, "okasinnsuke": 168, "Zeddy": 169, "Antinatalist": 170, "TazzaAje": 171, "CommandoPRO": 172, "Incurro": 173, "Gladen": 174, "TheR1senDead": 175, "PapaJason": 176, "CaimanLizard": 177, "stathisv13": 178, "Scorpion": 179, "ryanfgh5": 180, "Insom": 181, "Fosho": 182, "Batu": 183, "Ikkih": 184, "xavgoh": 185, "DevilMat": 186, "Matteo": 187, "babisOmegas": 188, "Firenoodle": 189, "felicia": 190, "UrbanLegend": 191, "ImAMonster": 192, "Regelian": 193, "JacoboX": 194, "Janos": 195, "noobsicle75": 196, "wabeka": 197, "Ryw": 198, "joe": 199, "IlBestio": 200}, "WLD": {"TC02": 1, "Memnarch": 2, "ConnerRia": 3, "Bodybuilder": 4, "Extram\u00f6nch": 5, "Lorthos": 6, "FahadSh": 7, "barricades": 8, "whenshon": 9, "Abcrst": 10, "UltimateGod": 11, "parzival2345": 12, "EpigPlayer": 13, "Cresselia": 14, "\u305f\u3089\u3070": 15, "Tyatsmr": 16, "ksr": 17, "Arawyn": 18, "Chfox": 19, "Aleph": 20, "corbett": 21, "Boostio": 22, "Coozer": 23, "Freeza": 24, "wtybillfan": 25, "Hazer": 26, "BombBurper": 27, "TerryGe": 28, "Qanik": 29, "Skeptimist": 30, "Photon": 31, "Arbitrary": 32, "Ajiten": 33, "IzumiSagiri": 34, "AtomicGyre": 35, "XxSkrubxX": 36, "Mentalistic": 37, "nhlnjfan1": 38, "fallout": 39, "LoveHina": 40, "Fuzi": 41, "DSRolls": 42, "Aether": 43, "decktech": 44, "Lorance": 45, "XxFroBro45xX": 46, "Aidan": 47, "cat": 48, "Epsilon": 49, "Pastafreak1": 50, "KremePuff": 51, "XORN": 52, "Sherry": 53, "Jonahrah": 54, "Royce": 55, "Jazphi": 56, "Bonemasher": 57, "Gambito": 58, "KingBilly": 59, "throb": 60, "Aaron": 61, "\u60aa\u9b54\u597d\u304d": 62, "\u307b\uff01": 63, "codoc": 64, "ChowTuR": 65, "HvS": 66, "\u304a\u3066\u3043\u304b": 67, "Skitlz": 68, "BoiBandido": 69, "Battlw": 70, "crucibulum": 71, "Swyft": 72, "Renchao": 73, "BlackMamba": 74, "KiillerTG": 75, "AzianPowah": 76, "DimtheLights": 77, "Van": 78, "Grondus": 79, "reerkat": 80, "SheikVII": 81, "Martian": 82, "Jjjjjjjj": 83, "iLeo": 84, "mooingsheep": 85, "Euskade": 86, "sjowyuicy": 87, "Edge2522": 88, "tempest124": 89, "Rob3r": 90, "RamonLH": 91, "Sarbanes": 92, "lugea": 93, "BLANCK": 94, "Sayube": 95, "AndreDaMassa": 96, "Xealph": 97, "schwal": 98, "GGDomesticus": 99, "YourEternal": 100, "TheBlindGuy": 101, "SirHS": 102, "keithnumbers": 103, "Rock1t": 104, "Shwitz44": 105, "MMMMMMMMMHMM": 106, "Guigemar": 107, "Berilio": 108, "Dracoslay": 109, "Mtgsquirrel": 110, "Kuro": 111, "Scrotezout": 112, "PedePano": 113, "Water": 114, "Wtflag": 115, "Cattywompus": 116, "\u0e19\u0e49\u0e33\u0e21\u0e19\u0e15\u0e4c": 117, "blisterguy": 118, "apple": 119, "Trapskii": 120, "chocolatebox": 121, "Ryla": 122, "HAISHESAMA": 123, "Jack": 124, "kakolokia": 125, "Grubby": 126, "Raddix": 127, "Spencer": 128, "DieInsect": 129, "Servex": 130, "Fresh": 131, "drpepperdawg": 132, "wizlian": 133, "\u01c2\u00ce\u013b\u0141\u01d9M\u00cf\u0145\u00c5\u0166\u00ce\u01c2": 134, "\u4f46\u613f\u4eba\u957f\u4e45": 135, "Woxbc": 136, "DBowie": 137, "Miguel": 138, "Titancat": 139, "OldSchoolVic": 140, "Shawn": 141, "Sambaz": 142, "StormCastle": 143, "jmarks": 144, "VQ2022": 145, "FierceDeity": 146, "Pendragon": 147, "Phage": 148, "ShiangChen": 149, "SeeDerekRun": 150, "Rybczynski": 151, "kaiobbd": 152, "CFR": 153, "GoRush": 154, "TheDoctor": 155, "Kordyon": 156, "CuakOn": 157, "Gifmekill": 158, "rageseid": 159, "Ruixiang": 160, "jepato": 161, "Pl4stic": 162, "dhtin": 163, "Toad": 164, "BattMasile": 165, "GaaRa": 166, "AuroraBlues": 167, "Purleta": 168, "Zeus": 169, "Trash": 170, "FAGUOREN": 171, "Inuchris": 172, "tobius": 173, "Nicro": 174, "KamChancelor": 175, "Nebu": 176, "Naji": 177, "Randles": 178, "Inman": 179, "JPCLima": 180, "Guanwen": 181, "FerdMito": 182, "RishadanPort": 183, "Murlocian": 184, "\u6768\u79c0\u5c01": 185, "AfraidGoblin": 186, "Edo": 187, "Joaquin": 188, "Strizyfe": 189, "BattleTagger": 190, "James13973": 191, "dArtagnan": 192, "LukeSkyCards": 193, "igna77": 194, "Killinger": 195, "konsortium": 196, "Brendan": 197, "AEnima": 198, "oceaneyes": 199, "OceanChamp": 200}, "BG": {"Waterloooooo": 1, "Champy": 2, "Utoko": 3, "Twlevewinshs": 4, "dog": 5, "Scrappity": 6, "ReporterHK": 7, "XDD": 8, "sjow": 9, "awedragon": 10, "DiyingLi": 11, "DrLazyEyes": 12, "Mats": 13, "Lii": 14, "touge": 15, "keromon": 16, "EducatedC": 17, "Audretsch": 18, "BeNice": 19, "Nowitzki": 20, "Kripptogay": 21, "yuma": 22, "Cherkash": 23, "Amam15": 24, "Kkekev6789": 25, "Fritterus": 26, "volatility": 27, "Vlyrd": 28, "Kookiez": 29, "EndoZoa": 30, "InfiniteWay": 31, "Mullibok": 32, "Katie": 33, "\ud2b8\uc704\uce58\ub9bc\uace0\uc218": 34, "vAyoVee": 35, "\u81ed\u81ed\u5730\u7cbe": 36, "tonizle": 37, "mrskeltal": 38, "Raze": 39, "\u307e\u30fc\u3084\u3055\u304b\u3082\u3068": 40, "lookformywif": 41, "Kwe": 42, "Xiaoming": 43, "JerryHan32": 44, "Duhbbleyou": 45, "Water": 46, "Staplers": 47, "HELLOxNASTY": 48, "GrimSk": 49, "ichijp": 50, "WobbleWeezy": 51, "Seniorheld": 52, "Scarab": 53, "Calimatt": 54, "mogura": 55, "NEVERLAND": 56, "dimazavr1k": 57, "Rich": 58, "HurryMyCurry": 59, "\u627f\u6cf0\u4e0d\u8981": 60, "Loukay": 61, "wtybill": 62, "Nerdblaster": 63, "Seba": 64, "shoop": 65, "Vendetta": 66, "Ponpata07": 67, "EducatedCeu": 68, "guDDummit": 69, "Boblarry": 70, "Srdjan": 71, "oliech": 72, "OneDay": 73, "pastaS": 74, "Creand": 75, "newbrid": 76, "\u5e25\u6c23\u7684\u5955\u54e5": 77, "\u0428\u0442\u0430\u043d\u0423\u0434\u0430\u0447\u0438": 78, "TwoBiers": 79, "ManiacMuffin": 80, "Roger": 81, "aCraj": 82, "Tomura": 83, "Tiesto": 84, "Snapcaster": 85, "wh24bmo34": 86, "AutumnWater": 87, "Purple": 88, "twohundredIQ": 89, "lllIlllIlllI": 90, "donutgames43": 91, "hz4873": 92, "Okaerinasai": 93, "dawntreader": 94, "Evakos": 95, "CreamyCorn": 96, "Emlur": 97, "axel": 98, "Daiteon": 99, "thedrap": 100, "Tobi": 101, "SouLdOut": 102, "Foooz": 103, "CaliforKing": 104, "Memi": 105, "Soylentsauce": 106, "Alphaferret": 107, "KingofChem": 108, "JasonCai": 109, "drizzle": 110, "undefined": 111, "Admirable": 112, "\u6b4c\u5cb8\u8a93\u8072": 113, "Alucard": 114, "Shun": 115, "jnmc2013": 116, "\u592a\u6781\u5251": 117, "MeowYutou": 118, "ryshoe": 119, "Magnechu": 120, "gosu": 121, "Dreamberg": 122, "SaphirexX": 123, "Kheffin": 124, "MasterBenObi": 125, "James": 126, "ssoonn": 127, "Yellow": 128, "SteeB": 129, "Ch95120": 130, "Wilson": 131, "\u883b\u53ef\u611b\u7684\u963f": 132, "bananabread": 133, "Fizz": 134, "VX14": 135, "Timogy": 136, "qeidcariahdf": 137, "dreads": 138, "Aldover": 139, "Shadybunny": 140, "Bruhffalo": 141, "charlie": 142, "Utall": 143, "RedChicken": 144, "SUrkil": 145, "Avista": 146, "\u4f60\u6709\u5565\u53ef\u8c6a\u6a2a\u7684": 147, "Desquall": 148, "koyomi": 149, "Turn3vsAFKay": 150, "Juiceamongus": 151, "JazzyChoi": 152, "IDontKnow": 153, "Letsfireitup": 154, "MechantHulk": 155, "bvbat": 156, "Polymorph": 157, "OccamsRazor": 158, "Lezah": 159, "rkz": 160, "Kerkoporta": 161, "Hatchett": 162, "Durpalurpa": 163, "JGOD": 164, "UnforgivnII": 165, "WumboStyle": 166, "RLanceGunnin": 167, "LightFlight": 168, "GbrO": 169, "TheDarkLink": 170, "Ace": 171, "Farroway": 172, "HALfaith": 173, "pqp": 174, "EnWeee": 175, "AdmiralSandy": 176, "patoyao": 177, "JSB": 178, "sleples": 179, "Pocky": 180, "LoveLove": 181, "danabeast": 182, "Hafu": 183, "Titan2019": 184, "Mystic": 185, "soonX": 186, "tori": 187, "Bamboo": 188, "IceFrozen": 189, "spagettitime": 190, "Terminating": 191, "shiro": 192, "\u4f60\u7684\u724c\u6389\u5730\u4e0a\u56c9": 193, "Lumpy2": 194, "i8therock": 195, "mashking": 196, "Nilatarion": 197, "eprinventone": 198, "Windyoyoyo": 199, "OdeioAggro": 200}}, "EU": {"STD": {"Gaby": 1, "DSIVAN": 2, "Amazing": 3, "SomiTequila": 4, "H\u00e9rosFunky": 5, "Stormbolt": 6, "Soxiik": 7, "RastaFish": 8, "Pepe": 9, "Furyhunter": 10, "Eclipse": 11, "PIONER": 12, "NikosFas": 13, "lattosio": 14, "Kal\u00e0xz": 15, "MJKing": 16, "HKroms": 17, "Rikitikitavi": 18, "star": 19, "Jarla": 20, "Theo": 21, "Youth": 22, "Memory": 23, "Meati": 24, "DeathsFathom": 25, "JEJBenkoJEA": 26, "SoleniumSol": 27, "Zany": 28, "glory": 29, "Bangaranger": 30, "WEStone": 31, "Zoltan": 32, "AuRon": 33, "CrazyMage": 34, "Sprite974": 35, "Norwis": 36, "felicia": 37, "Player671": 38, "IceWizard": 39, "From0tohero": 40, "Shagura": 41, "\u041f\u0430\u0448\u0430\u0422\u0435\u0445\u043d\u0438\u043a": 42, "Wolder": 43, "panas1998": 44, "Hawkeye": 45, "Zeeland": 46, "DeadDraw": 47, "Cironutts": 48, "jambre": 49, "petrovic": 50, "BlessTheFall": 51, "NORE": 52, "wiRer": 53, "Orange": 54, "Panakas7": 55, "smthblue": 56, "Maxxe": 57, "hunterace": 58, "Paljuha": 59, "Leta": 60, "Snicker": 61, "Zuhex": 62, "EverYoung": 63, "CelikQ": 64, "stathisv13": 65, "FreddyB": 66, "BruTo": 67, "StrikeReaper": 68, "SaucisseSwan": 69, "Crane333": 70, "Pilux": 71, "Bunnyhoppor": 72, "Flix": 73, "XiaoT": 74, "nadavt": 75, "Darkstrike": 76, "TheBest": 77, "RangoB": 78, "Fantomer": 79, "Nico2108": 80, "Deathwing": 81, "Flop": 82, "LayLadyLay": 83, "WetGoose": 84, "ChaboDennis": 85, "Jokersim": 86, "Rase": 87, "Dasuap": 88, "NONOkiller": 89, "bieberfever": 90, "Vonny": 91, "g\u00e9t\u00e9": 92, "ZAM": 93, "Thavo": 94, "levik": 95, "Tortue": 96, "Markelos": 97, "OrcMalade": 98, "PocketTrain": 99, "Merkman": 100, "Dazzar": 101, "Turna": 102, "pokrovac": 103, "C1trus": 104, "Matty": 105, "Samsa": 106, "Dizdemon": 107, "ArkZX": 108, "dawido": 109, "DenimBlue7": 110, "tamama": 111, "plastiik": 112, "Juristis": 113, "Minislash": 114, "Zyrios": 115, "Wraziel": 116, "LeeroyStark": 117, "RENMEN": 118, "\u0434\u0430\u0440\u043a": 119, "Frenetic": 120, "TheBoss00": 121, "Affie": 122, "tholwmenos": 123, "Giovi02": 124, "PWNZ": 125, "Atan": 126, "Cptnkitty": 127, "Blackhole": 128, "L\u00e9opold": 129, "Alpis": 130, "MadDemon": 131, "M1LAN": 132, "IdanProK": 133, "Maverick": 134, "etovityusha": 135, "DerBass": 136, "DeadUndead": 137, "Sveiks": 138, "\u0423\u0448\u043b\u044b\u0439\u0421\u0442\u0440\u0430\u0443\u0441": 139, "Jobeland": 140, "Sezoklo": 141, "Nagib": 142, "Trusted": 143, "Dotage": 144, "FIvanovic": 145, "Nlky": 146, "Nightning": 147, "Nightmare": 148, "AndreiRO": 149, "BongDaCity": 150, "Razer": 151, "Destructor13": 152, "GeneralC": 153, "voEz": 154, "Hazarder": 155, "Nova": 156, "Kammi": 157, "TH3G3NTL3M4N": 158, "Leas": 159, "lex": 160, "ZheDude": 161, "Incurro": 162, "Dasta00": 163, "battletag": 164, "Fenomeno": 165, "Louisdebou": 166, "I984isnow": 167, "Wuncler": 168, "bo0bs": 169, "kondrash228": 170, "\u0414\u0438\u043a\u0438\u0439\u0417\u0432\u0435\u0440\u044c": 171, "Dunkadoodle": 172, "LordOleg": 173, "Benz0l39310": 174, "Ajani": 175, "Pignas": 176, "FrostTitan": 177, "Marusak": 178, "SkyPCFree": 179, "lowseeker": 180, "Alxx": 181, "WALRUS": 182, "Neirea": 183, "Maur1": 184, "Filobassi03": 185, "didi1234": 186, "Marcou": 187, "HornetGR": 188, "YouKnowWP": 189, "Xawko": 190, "HiImJoZo": 191, "Darq7007": 192, "CptBoatsNHoe": 193, "SpinaLogaMan": 194, "Martyr": 195, "Menny": 196, "Dreinak": 197, "Charon": 198, "Malakadiez": 199, "polilop": 200}, "WLD": {"Lorthos": 1, "DerBass": 2, "BoomBewm": 3, "Hijodaikan": 4, "Lasagne": 5, "XxFroBro45xX": 6, "e2718": 7, "Robert260": 8, "ZAHASMADAN": 9, "RallerB": 10, "Huker": 11, "MysticWolf": 12, "Badmanis": 13, "balance": 14, "zCthulhu": 15, "AzureWrath": 16, "MyLittleHell": 17, "tauntischeat": 18, "Cresselia": 19, "NiKo": 20, "PiggyMcCool": 21, "Beholder": 22, "Ryla": 23, "Nairamus": 24, "BlackMamba": 25, "\u6771\u5317\u4e94\u5927\u4ed9": 26, "Halliron": 27, "Nazgxl": 28, "DeMatteis": 29, "\u6768\u79c0\u5c01": 30, "Ghost": 31, "Qanik": 32, "synteck": 33, "Montanaz0r": 34, "tutur": 35, "Goku": 36, "Shad0wForg3": 37, "SmellyHuffer": 38, "RubentjeW": 39, "CrazyMelon32": 40, "\u305f\u3089\u3070": 41, "Ruixiang": 42, "ZbigniewJe\u017c": 43, "\ub85c\uadf8\uc544\uc6c3\uc880\ud574\ub77c": 44, "BlueVenser": 45, "Biox": 46, "MELNYK": 47, "Alb987": 48, "BlackArcher": 49, "Yogg": 50, "antehero": 51, "JADAPEGA": 52, "KremePuff": 53, "dimitris1200": 54, "Serval99": 189, "Sandor": 56, "Spirituus": 57, "Jutcher": 58, "SgtSlay3r": 59, "zlidaCaosgi": 60, "Zico": 61, "Shadowverse": 62, "Ramses": 63, "RewaT": 64, "g\u00e9t\u00e9": 65, "Azazel": 66, "AyzZer": 67, "MeD": 68, "cendros": 69, "Farcor": 70, "Evgeny": 71, "SaintPablo": 72, "H4771W4771": 73, "Demonized": 74, "StandinSoe": 75, "Charcoal": 76, "TeepTop": 77, "Dre": 78, "\u53d9\u8bfa": 79, "Beasty": 80, "wilym4n": 81, "GiBiLaN": 82, "Traggol": 83, "RainStorm": 84, "mcmpan": 85, "MajorTom": 86, "Pax": 87, "Bastounas": 88, "irini": 89, "Bruce": 90, "AdoSensei": 91, "Fenrir": 160, "JuZam": 93, "Rivenic": 94, "Mathsman": 95, "mao": 96, "K1ll3": 97, "Morph": 98, "SirPuFFaRiN": 99, "Interlender": 100, "Wookie": 101, "Finalfrenzy": 102, "Xenom": 103, "Bellyguru": 104, "keithnumbers": 105, "Miisders": 106, "SegaGoWild": 107, "Rokasa369": 108, "Curian": 109, "Lelouchdu17": 110, "dielange123": 111, "ExiWake": 112, "Rathma": 113, "Sebokooo": 114, "\u0421\u043c\u0435\u0440\u0442\u043e\u043c\u044b\u0448\u044c": 115, "NoHope": 116, "Osammotyogg": 117, "battleman": 118, "Roszinchen": 119, "Crossbread": 120, "miKL": 121, "Aaron": 122, "Edo": 123, "TheGreatGoku": 124, "Slayer": 125, "HKisCHINESE": 126, "andygmr": 127, "\u0417\u0430\u0447\u0435\u043c": 128, "Chemfox": 129, "Aqua7": 130, "Mumbles": 131, "INTEFIX": 132, "Nikolay": 133, "Imbizile": 134, "bukibuki": 135, "Nirvana": 136, "Meisender": 137, "DragoshhhxD": 138, "EpicPoulp": 139, "Dario": 140, "TodesHauch": 141, "MMMMMMMMMHMM": 142, "Uzmusiu": 143, "SMOrc": 144, "romekziomek": 145, "ZeNoLifeKing": 146, "Ryo94": 147, "Freemantle": 148, "DaboBabo": 149, "MOLTE": 150, "Mantihor": 151, "ShadowKiller": 152, "Emeric": 153, "Lorance": 154, "DarkGlow": 155, "Lisa": 156, "L1s": 157, "tsudecimo": 158, "\u041f\u0438\u0442\u0443\u0448\u043e\u043a743": 159, "Heisenberg": 161, "Towelie": 162, "GoldVip": 163, "Malekith": 164, "Kaiser": 165, "Mistermatrix": 166, "poseydon": 167, "MEMhunteR": 168, "Karolos": 169, "POTGStealer": 170, "Adinawina": 171, "ALDR": 172, "JambaJooze": 173, "mikethewolf": 174, "IanLeBruce": 175, "soraichigo95": 176, "wny0202": 177, "Unforgiven": 178, "pyrogein": 179, "borubar": 180, "\u0421\u0435\u043a\u0442\u043e\u0440\u0413\u0430\u0437\u0430": 181, "Ramzii": 182, "Grattak": 183, "Pingouin": 184, "Extram\u00f6nch": 185, "Tinno": 186, "kuurby89": 187, "Wuncler": 188, "ClawViper": 190, "creamfield": 191, "Nightcore": 192, "Sandy": 193, "TyRewOw": 194, "sandsofsea": 195, "Jason": 196, "Todesschabe": 197, "Cubyyy": 198, "Kaito": 199, "Feriman": 200}, "BG": {"alexisdiesel": 1, "Seniorheld": 2, "Izyum": 3, "TypicalHanz0": 4, "Utoko": 5, "gleban1ster": 6, "Totelius": 7, "Xixo": 8, "Merlin": 112, "Habugabu": 10, "Mats": 11, "leminimoi": 12, "sjow": 13, "tajsama": 14, "BeNice": 15, "awedragon": 16, "DoGBiscuit": 17, "guDDummit": 18, "oliech": 19, "Tanerman": 20, "AiNyan": 21, "MindSniper": 22, "ErA": 23, "CuttinoYes": 24, "Jackmout": 25, "WobbleWeezy": 26, "Loukay": 27, "SilverName": 31, "pinkpants": 29, "Rendeil": 30, "thegamer97": 32, "Amroth": 33, "Epos": 34, "DeathItself": 35, "Goingy": 36, "sahar1337": 37, "EvgenyT": 38, "Simon": 39, "Ajay": 40, "Fritterus": 41, "Fourmizzz0": 42, "AppleZoom": 43, "dmccabe": 44, "mroczekOO": 45, "Kell": 46, "GNplayer": 47, "Excellent": 48, "Vectral": 49, "Arenste": 50, "Dule": 51, "DamiDeMa": 52, "Swiftending": 53, "\u0421\u044b\u043d\u0421\u043e\u0431\u0430\u043a\u0438": 54, "LegendHero": 55, "BouncyBear": 56, "TwoBiers": 57, "Rogojine": 58, "Felkeine": 59, "CrazyMonkey": 60, "ThegreatDLP": 61, "Pursuer": 62, "johnnyboy": 63, "wtybill": 64, "est123": 65, "Pessimist": 66, "DHawk": 67, "Trickster7": 68, "CookMySock": 69, "ssoonn": 70, "ixxdeee": 71, "Cherkash": 72, "Wa1lrider": 73, "Nitrogun": 74, "TheWhiteWolf": 75, "RobotWizard": 76, "Belial": 77, "Guccik": 78, "Stormy": 79, "Waterloooooo": 80, "piterKID": 81, "Sinedd92": 82, "ggarbi": 83, "Cleftor": 84, "first": 85, "Ray": 86, "Lamp": 87, "weiyo": 88, "thegnome": 89, "lllIlllIlllI": 90, "Dethearoc": 91, "Leps": 92, "honinbo7": 93, "Lesterberne": 94, "z3x59": 95, "fishou": 96, "Rdu": 97, "Bunnyhoppor": 98, "BQB": 99, "Mineralbad": 100, "Lichking": 101, "calin": 102, "Malisar": 103, "\u041c\u0438\u043a\u0440\u0438": 104, "DAMO93": 105, "\u0428\u0442\u0430\u043d\u0423\u0434\u0430\u0447\u0438": 106, "DebeliNitkov": 107, "SBackflip": 108, "Palsteron": 109, "Muggles": 110, "traceb": 111, "Siercke": 113, "MeanyGreeny": 114, "AhmetPro": 115, "Dinoel": 116, "ItsBen": 117, "Synoptic": 118, "Tubz": 119, "Revelation": 120, "itfyso": 121, "Nilatarion": 122, "park": 123, "Canny": 124, "Zorg": 125, "Kyzmich": 126, "Kreml": 127, "DxDoc": 128, "Koxik": 129, "balguard": 130, "genetic": 131, "KAREEV12k": 132, "Artemink": 133, "YourOpponent": 134, "VitaPrivata": 135, "JazzyChoi": 136, "grossmaster": 137, "Decksloth": 138, "shika": 139, "LatinT": 140, "shlaSasha": 141, "XQN": 142, "Nef1ida": 143, "\u041a\u0440\u0430\u0431\u0435": 144, "genau": 145, "Flank": 146, "charlie": 147, "marcinx": 148, "Minder": 149, "\u0427\u0430\u0439\u043a\u0430\u042f\u0440\u043e\u0441\u043b\u0430\u0432": 150, "LukasKobe": 151, "Beherit": 152, "Peitsche": 153, "Zazoo": 154, "JimTukif": 155, "Poskimasa": 156, "mrskeltal": 157, "Champy": 158, "FunkyFish": 159, "skennen": 160, "Moses170": 161, "MrBlack": 162, "bocharik": 163, "Hohol": 164, "mroczek00": 165, "AgraveiN": 166, "nordlic": 167, "Ross27ross": 168, "CHINAFAN": 169, "oroff": 170, "irohabit": 171, "Needlewars": 172, "Yipikaya": 173, "Bakel": 174, "IDDI": 175, "Ziezor": 176, "Budilicious": 177, "WalrusJuice": 178, "SirSalty": 179, "Exotic": 180, "Farroway": 181, "whinindog": 182, "TheJoeSen": 183, "fairywoody": 184, "Syophan": 185, "ARION": 186, "Verveine": 187, "Vermish": 188, "sleeepyyyyyy": 189, "ProblemChild": 190, "shyr0": 191, "Kreanicus": 192, "KalleAlter": 193, "MindMint": 194, "Brendumb": 195, "Firesterz": 196, "Djool": 197, "MonaLisaAnn": 198, "Ansters": 199, "RaistJ": 200}}, "AP": {"STD": {"Che0nsu": 1, "BlizzconJan": 2, "\u5c71\u4e0b\u667a\u4e45": 3, "Flandre": 4, "Allen": 5, "Garchomp": 6, "Zarathustra": 7, "shanOz": 8, "Tredsred": 9, "shuzoDS": 10, "mishail": 11, "Tansoku": 12, "Thund3r": 13, "Nightning": 14, "fire": 15, "Turner": 16, "VickeBlanka": 17, "IFBreak": 18, "XiaoDai": 19, "\u5247\u9f8d\u4e4b\u738b": 20, "BlackSureRap": 21, "RaFaEl": 22, "\ud53c\uc544\ub258\uc2a4\ud2b8": 23, "\u9f9c\u6bdb\u8001\u982d": 24, "Kongtan": 25, "Rey": 26, "TazzaAje": 27, "LoNa": 28, "MegaGliscor": 29, "oyatsu": 30, "Zuhex": 31, "lambyseries": 32, "ADU": 33, "Cassio": 34, "\ubb34\uc11c\uc6b4\ub4dc\ub8e8": 35, "\ub77c\uc774\uc5b8": 36, "etovityusha": 37, "SeolDaBi": 38, "Sergiy": 39, "maxchen": 40, "NAGON": 41, "takas": 42, "hone": 43, "En1gma": 44, "Lokyin": 45, "Kowsai": 46, "\ub3d9\uae30\ub9c1": 47, "Palmblad": 48, "\u30e6\u30a4": 49, "yeschicken": 50, "Reliquary": 51, "LLIoKoJIaD": 52, "zlsjs": 53, "rascal": 54, "\u718a\u5927\u4e0a\u83dc\u82f1\u6587": 55, "LzJohn": 56, "SithX": 57, "Fungggg": 58, "tnraAy": 59, "SGAhIce": 60, "\ub0ad\ucc9c": 61, "Alutemu": 62, "Klender": 63, "Ryvius": 64, "TIZS": 65, "\ub354\uc2a4\ud2f4": 66, "Taesang": 67, "\u3048\u308b\u3082\u3042": 68, "SpinaLogaMan": 69, "\uc794\uc545\ubb34\ub3c4\uc720\uad00\uc6b0": 70, "\ub178\ub780\ucf54\ucf54\ub11b": 71, "\uc624\ube60\ucc28": 72, "okasinnsuke": 73, "HAYATA": 74, "Asuka": 75, "\uc0b4\uc544\uc788\ub294\uc591\uc2ec": 76, "\u306b\u307c\u3057": 77, "Sooni": 78, "Flurry": 79, "herusia": 80, "WetGoose": 81, "\ucfe8\ub808\uc878\ud230": 82, "lowseeker": 83, "IdanProK": 84, "jail": 85, "strikeright": 86, "OVERWATCH": 87, "SellyX": 88, "\ubb34\uc5d0\uc11c\uc720\ucc3d\uc870": 89, "\u30ac\u30c1\u9234\u6728": 90, "\uc2ac\ud37c\ud558\uc9c0\ub9c8\ub178\ub178\ub178": 91, "youngjoon": 92, "PinkiePie": 93, "Duyyy": 94, "\ud558\uc774\uc5d4\uc544": 95, "ostinato": 96, "Faeli": 97, "woziny": 98, "Jay": 99, "tamama": 100, "GundamFlame": 101, "posesi": 102, "Aaron": 103, "Vinz": 104, "Paradox": 105, "\uae08\uc694\uc77c": 106, "MANHATTAN": 107, "Norwich": 108, "\u6492\u65e6\u964d\u81e8": 109, "Seulsiho": 110, "horo": 111, "Salmon": 112, "Tangler": 113, "\u305f\u3089\u3070": 114, "kevin": 115, "\u5929\u4e0b\u4e00\u535a\u5f92": 116, "Definition": 117, "kin0531": 118, "ulza8102": 119, "Nature": 120, "\uae40\ub2e4\ud604": 121, "Yishiki": 122, "\uae40\ub3d9\ubbfc": 123, "\uc9c4\uc6d0\uce58\ud0a8": 124, "DragonMan": 125, "recoco": 126, "Dcon": 127, "ARAI": 128, "Zenith19": 129, "Dizdemon": 130, "Tobyka": 131, "TheViper94": 132, "blitzchung": 133, "\ub3d9\ubb34\ub8e9": 134, "coolkid2001": 135, "BKILL": 136, "\u4f0a\u85e4\u5712": 137, "\u30d7\u30e9\u30b9": 138, "Winter": 139, "ohtani3": 140, "\uce74\ub974": 141, "\ucd5c\uc11d\uc911": 142, "Eclipse": 143, "tomof": 144, "\u307c\u3093": 145, "Jojoon": 146, "glory": 147, "\u0414\u0438\u043a\u0438\u0439\u0417\u0432\u0435\u0440\u044c": 148, "\u897f\u9675\u73e9": 149, "\uc544\uc2dc\ud750": 150, "Nada": 151, "Kongkim": 152, "\u3057\u3093210": 153, "\uc74c\uc800\ubc94": 154, "\u9999\u83c7\u597e\u6c41": 155, "Hi3": 156, "kuroma": 157, "Ares": 158, "lattosio": 159, "VirtuozZ": 160, "stathisv13": 161, "funashi": 162, "Gaboumme": 163, "\uc11d\uc6d0": 164, "tom60229": 165, "Hibadino": 166, "calisolo": 167, "Alena": 168, "Gonu": 169, "\uc720\uc6cc\ub9ac": 170, "MrTen": 171, "\uc2e0\uba85\uc218": 172, "\ubc14\ub8e8\uc2a4": 173, "choco06743": 174, "BlueBlood": 175, "peAl": 176, "Mikka": 177, "Harash": 178, "YuSheng": 179, "Ruke": 180, "\uc624\ud1a0": 181, "\uc5d0\ub81b\uc9c0\ub514": 182, "HyunMini": 183, "Eveliss": 184, "Chamomile": 185, "Foot": 186, "\u9280\u98a8": 187, "\uc774\ub3d9\uc6b1": 188, "WuLing": 189, "\ub784\ub3d9": 190, "Dream": 191, "\ub808\uc804\ub4dc": 192, "Metamorphose": 193, "Tinaaa": 194, "steeloslave": 195, "taroimo": 196, "sasag": 197, "NeGatiVesiX": 198, "DimitriKazov": 199, "IrvinG": 200}, "WLD": {"paradox": 1, "Thundurus": 2, "\u6768\u79c0\u5c01": 3, "chocolatebox": 4, "autolytic": 5, "\u5f88\u661f\u7206\u4f60\u77e5\u9053\u55ce": 6, "Ghostdog": 7, "miraieigo": 8, "\ube44\ub2f4": 9, "\uc5b4\ub290\ud654\ucc3d\ud55c\ubd04\ub0a0": 10, "Cresselia": 11, "Suicune": 12, "Kangaskhan": 13, "Breloom": 14, "Ajiten": 15, "\u963f\u4e00\u4e0d\u5c0f\u5fc3": 16, "\u59eb\u67ca\u96ea\u83dc": 17, "\uc18c\uc2ec\uc7c1\uc774": 18, "\u305f\u3089\u3070": 19, "\u5047\u6148\u60b2": 20, "LucyVanPelt": 21, "\ube59\uc11c\ub9ac": 22, "\u30d2\u30ab\u30ea": 23, "\u30ad\u30e9\u30fb\u30e4\u30de\u30c8": 24, "\ub4dc\ub9bc\uce74\uce74\uc624": 25, "Lorthos": 26, "\u30b5\u30f3\u305f\uff5e\uff01\uff1f": 27, "BGO": 28, "\ucd08\uac15": 29, "\u591c\u6953": 30, "RexChou": 31, "Ryla": 32, "\u3072\u3083\u304f\u3042\u3093\u3053": 33, "\uc6b0\uc4f0\uc774": 34, "\uc740\ube5b\ub9e4": 35, "\ud2b8\ub864\ub7ec\uc26c": 36, "\uc624\ub9ac\uc0ac\ud574\uc92d": 37, "PLoN": 38, "Lee1k": 39, "\u3068\u3093\u3071\u3061": 40, "\u61a4\u6012\u86cb": 41, "MiLaDy": 42, "sealhoon": 43, "\u71c1\u9b54": 44, "\ub4dc\ub808\uc774\ube10": 45, "Marion": 46, "sHowTime": 47, "\u30de\u30c3\u30c1\u30e7": 48, "element91": 49, "plastic": 50, "TadokoroKoji": 51, "SleepyBear": 52, "Jonahrah": 53, "balance": 54, "meguru": 55, "CroaLaAisha": 56, "\u9999\u6e2f\u4eba": 57, "misumin777": 58, "kitakami": 59, "\u3072\u306a\u3061\u307e": 60, "Antithese": 61, "YsLiang": 62, "BKILL": 63, "Shadowverse": 64, "Laphroaig": 65, "Flare": 66, "Clemmy": 67, "\uc758\ubbf8": 68, "\uc0ac\ubb3c\ud568\uadf8\uc790\uccb4": 69, "rui": 70, "JohnZaller": 71, "\ucd08\ub85d\uac00\uc2dc\uc5c9\uac85\ud034": 72, "signal": 73, "\u8972\u6ec5\u5929\u4f86": 74, "unun": 75, "DieInsect": 76, "galvatron": 77, "kid": 78, "\u3071\u3063\u3064\u3041\u3093": 79, "KremePuff": 80, "\uba58\ud0c8\ub9ac\uc2a4\ud2b8": 81, "\uc870\uc6b4": 82, "\ubb34\uc2a8\uac01\uad81\uac01\ub108\ud504\uac01": 83, "\uc0ac\uacfc\ub2f9": 84, "BlackMamba": 85, "\ub0b4\ub798\uc0c1\uba74\uc774\uc57c": 86, "EEEx": 87, "Pow": 88, "Rusthishiro": 89, "alwaysthanks": 90, "UltraM": 91, "Shalashaska": 92, "Arc": 93, "\ubaa9\ub9c8\ub978\ubaa9\uc694\uc77c": 94, "\u591c\u9ed1": 95, "\u6307\u53c9\u7403": 96, "\u5929\u4e0b\u4e00\u535a\u5f92": 97, "\u3061\u304f\u308f\u5927\u660e\u795e": 98, "freakynizzle": 99, "Signal": 100, "\uc624\ub3c4\uc544\ucf00\ub974": 101, "Absolutely": 102, "oimo": 103, "kirikiri": 104, "SHINY": 105, "\u6297\u97e9\u4e2d\u5e74\u4eba": 106, "\uc0c8\ubcbd\ub2ec\ube5b\ud5a5\uae30": 107, "Jack": 108, "llllllllllll": 109, "brightsaint": 110, "malo": 111, "\u3066\u3064\u304b": 112, "\u30ea\u30c8\u30eb\u30c7\u30e2\u30f3": 113, "\u8840\u98a8\u9913\u72fc": 114, "flugel": 115, "\u91cc\u5bae\u838e\u7b71": 116, "stelmosfire": 117, "Money": 118, "teruteruboy": 119, "SOL": 120, "\uc778\uc0dd\ub9ac\ub864": 121, "stov2": 122, "KFII": 123, "antehero": 124, "Senior5": 125, "\u4f0a\u9732\u6069": 126, "Empty": 127, "tomtom1021": 128, "Yogurt": 129, "Zephyr": 130, "Daydream": 131, "momo": 132, "\u6905\u5b50": 133, "Issac": 134, "Pl4stic": 135, "MothballOrz": 136, "\ub85c\uc2a4\ud130\ud328\uce58": 137, "Cairne": 138, "summus": 139, "BubuB": 140, "Ture": 141, "Assy": 142, "\ud0dc\uc870\uc0f7\uac74": 143, "\uc5d8\ub80c\ub514\uc57c": 144, "\u5115\u54e5": 145, "\uba54\ub9ac\ud074\ub9ac\uc2a4\ub9c8\uc2a4": 146, "Thijs": 147, "Newstyle": 148, "lkhoward": 149, "WaIl": 150, "\u3086\u3058\u304d": 151, "\uac04\uc9c0\ubcf8": 152, "Weiss": 153, "\uc81c\uac08\ub7c9": 154, "JKCC": 155, "overdrug": 156, "Doby": 157, "AuroraRun": 158, "\ud64d\uaddc\ub2c8": 159, "Extram\u00f6nch": 160, "Dopa": 161, "\uc778\uc131\uc9c8\ub85c\ubd07": 162, "Excelia": 163, "DeathG0d": 164, "Metamorphose": 165, "Nemo": 166, "\ud61c\uc548": 167, "\uc2dc\uc988": 168, "Barther": 169, "Saxchoi": 170, "\u3068\u307f\u3044\u3061": 171, "\uc2dc\ud5cc\uc4f0": 172, "SuperNinja": 173, "Bruce": 174, "mars": 175, "Cafka": 176, "GalaxyKaiKai": 177, "linkinhoi": 178, "MiniNinja": 179, "knightstory": 180, "\u307e\u305f\u305f\u3073": 181, "\uc218\ube44\uc601\uc6c5": 182, "willie": 183, "\ucca0\uad8c\uc655\uc544\uba38\ud0b9": 184, "guard1019": 185, "Calvin": 186, "\ubca0\uc2a4\ud540\uac00\uc2a4": 187, "Jackling": 188, "\u708e\u6590": 189, "steeloslave": 190, "\ub9c9\uac15\ud55c\uc62c\ube7c\ubbf8": 191, "Alsyboy": 192, "\u30ab\u30fc\u30bd\u30eb": 193, "\uae40\ub098\uc8fc": 194, "\uace0\uc9c0": 195, "YangZhitian": 196, "Edo": 197, "tpeatcmike": 198, "juvenilia": 199, "\uc6cc\uc9c0": 200}, "BG": {"\u30da\u30f3\u30ae\u30f3\u3055\u3093": 1, "Ace": 2, "\u30c6\u30aa": 3, "\u30eb\u30d4\u30b3\u306e\u7236\u3067\u3059": 4, "\uc131\uc778\ud604": 5, "\u627f\u6cf0\u4e0d\u8981": 6, "AndreaPsv": 7, "obake": 8, "Portia": 9, "LKW": 10, "\u30c6\u30bc\u30ec\u30c3\u30c8": 11, "\u9ed1\u9727": 12, "\u6b4c\u5cb8\u8a93\u8072": 13, "Ponpata07": 14, "\uacf5\uae30\uba39\uace0\uccb4\ud568": 15, "\u3064\u304f\u306d": 16, "\u5927\u982d\u76ae": 17, "SeseiSei": 18, "\u7720\u304f\u306a\u3044\u3067\u3059": 19, "HuRu": 20, "\uff13\uff11\uff10\uff14": 21, "haguren": 22, "Yoshikage": 23, "\ud2b8\uc704\uce58\ub9bc\uace0\uc218": 24, "Alza": 25, "setukiti": 26, "\uc560\uc624\uac1c": 27, "\u3070\u304b\u3058\u3083\u306a\u3044": 28, "ssoonn": 29, "Guchin": 30, "\u5e25\u6c23\u7684\u5955\u54e5": 31, "perochan": 32, "\u98c4\u98c4": 33, "ASuN": 34, "\ub3c4\ud1a0\ub9ac\ubb35": 35, "\u6020\u60f0\u306a\u308b\u30ab\u30e1": 36, "naru": 37, "dionysus": 38, "mizca": 39, "\u5c0a\u5929\u5929": 40, "MATSURI": 41, "\u767d\u3046\u3055": 42, "\uc545\uc5b4\uc720\ud29c\ube0c": 43, "drizzle": 44, "Knight": 45, "Maplefire": 46, "apple": 47, "RiveraJP": 48, "\uac80\uc740\ub108\uad6c\ub9ac": 49, "\ubc34\ube0c\ub85c\ub4dc": 50, "kavan753120": 51, "ttvBebe872": 52, "\uff33\uff2e\uff33\uff24": 53, "BixchRabbit": 54, "takashi": 55, "CaliforKing": 56, "Nob": 57, "Luna": 58, "Mokkosu": 59, "WaterMelon": 60, "Hyanum": 61, "\ud574\ud45c": 62, "\u30a2\u30ba\u30e2": 63, "harmy": 64, "bbqgg": 65, "zinrai22": 66, "\uc544\uc774\uc720": 67, "jaziringo": 68, "moai1024": 69, "Lastword": 70, "djenddl": 71, "torisan": 72, "TeeB": 73, "Sen": 74, "\u3042\u3042\u3042\u3042": 75, "Red": 76, "minato": 77, "alan": 78, "\u81ed\u81ed\u5730\u7cbe": 79, "\u5609\u795e\u5ddd\u30af\u30ed\u30a8": 80, "\ube5a\uc9c4\uc790": 81, "Comet": 82, "\u4f60\u5168\u5bb6\u90fd\u61a4\u6012\u96de": 83, "satotsu270": 84, "\uc5b8\uc624\ub9ac": 85, "qeidcariahdf": 86, "Perusan": 87, "\u6700\u5f8c\u306e\u30e2\u30a4\u30e9\u30de\u30f3": 88, "BlackDevil": 89, "\u3042\u308c\u3063\u304f\u3059": 90, "akitumn": 91, "poteto": 92, "\u4e0d\u673d\u6230\u795e": 93, "TIZS": 94, "wtybill": 95, "\u30de\u30b0\u30cc\u30b9": 96, "\ub9cc\uad70\uc758\uc8fc\uc5ec\ud638\uc640": 97, "OSAPIX": 98, "\uc2dd\uae30\uc138\ucc99\uae30": 99, "lookformywif": 100, "muvze": 101, "\u91ce\u751f\u306e\u96d1\u7a2e\u72ac": 102, "Surrender": 103, "\u30c8\u30fc\u30ec\u30b9": 104, "LTW": 105, "CersNovice": 106, "Grayn1869": 107, "\ub810\ub984\ub2e4\uc6b4": 108, "proust": 109, "\u6211\u5bb6\u4f4f\u5728\u5bcc\u5ca1": 110, "Farroway": 111, "Sato9kado": 112, "IRIS": 113, "\u715e\u6c23\u963f\u7fd4": 114, "kuromatu": 115, "Teke": 116, "rance": 117, "\ud074\ub9b0\uc720\uc800": 118, "nifu": 119, "kio": 120, "tom60229": 121, "summoner": 122, "namil": 123, "\uc5ec\uad00\uc8fc\uc778": 124, "\u30b7\u30e9\u30a4": 125, "nukesaku": 126, "\u883b\u53ef\u611b\u7684\u963f": 127, "Suckboy": 128, "DeadlyPants": 129, "\ucca0\uba74\uc218\uc2ec": 130, "KYlin": 131, "\ub9ac\ubc14\ud478\uc0ac": 132, "\ub9ac\ud638": 133, "\ucf69\ub8e8\ud0a4": 134, "\u53f3\u4e8c\u4fe0": 135, "caster": 136, "Narchi": 137, "estell": 138, "\u66b4\u96ea\u4f60\u5a18\u5e6b\u6211\u5438\u5c4c": 139, "\uce58\ud0b9": 140, "\u5361\u5fc3\u73e0\u59ec\u59ec": 141, "StatPeter": 142, "mixx": 143, "GiantAxe": 144, "HHC": 145, "konijiwa": 146, "Berry": 147, "Roger": 148, "Vmasafumi": 149, "O3O": 150, "l1l1l1l1l1": 151, "AleYellowHat": 152, "gosu": 153, "a4577777": 154, "\u4e0d\u8981\u53eb\u9192\u6211\u597d\u55ce": 155, "ElectricSix": 156, "Tiesto": 157, "SimToong": 158, "hanhanr": 159, "\u795e\u62bd\u5230\u4f60\u5d29\u6f70": 160, "Daser": 161, "NaWheel": 162, "\u307f\u3075\u3041\u3048\u308b": 163, "WaKo": 164, "OscarTaveras": 165, "PEI": 166, "blackorc": 167, "qwerty": 168, "YAMAGAMI": 169, "GoodDay": 170, "Aserora": 171, "Kimmy": 172, "\uc751\uc560\uc138\ub825": 173, "pianolkiller": 174, "eun5080": 175, "Pidgeotto": 176, "EducatedC": 177, "\uacc4\ud53c\ub9db\uc2a4\ucf58": 178, "BreakOutLYS": 179, "sunaji": 180, "chorek": 181, "\uc0ac\ub0e5\uafbc": 182, "Duelist": 183, "Zimply": 184, "Satellite": 185, "dawowa": 186, "\u304b\u3089\u3059": 187, "Yanlex": 188, "\ub3d9\ubb34\ub8e9": 189, "\u62c9\u9eb5\u5230\u5473": 190, "\u9ad8\u901f\u5438\u5f15": 191, "rado": 192, "\u5f01\u5929": 193, "hirokip": 194, "Ariadne": 195, "hatashin": 196, "jkirek": 197, "\u304d\u3055\u304e": 198, "NewCz60229": 199, "geso": 200}}}